realerikrani/flaskapierr/__init__.py
realerikrani/flaskapierr/error.py
realerikrani/flaskapierr/error_handler.py
realerikrani/flaskapierr/py.typed
realerikrani_flaskapierr-1.0.0.dist-info/LICENSE
realerikrani_flaskapierr-1.0.0.dist-info/METADATA
realerikrani_flaskapierr-1.0.0.dist-info/WHEEL
realerikrani_flaskapierr-1.0.0.dist-info/top_level.txt
realerikrani_flaskapierr-1.0.0.dist-info/RECORD
