Metadata-Version: 2.1
Name: realerikrani-flaskapierr
Version: 1.0.0
Summary: Error handling models and functions for Flask-based APIs
License: Apache-2.0
Project-URL: Repository, https://github.com/realerikrani/flaskapierr
Requires-Python: >=3.11
License-File: LICENSE
Requires-Dist: werkzeug==3.*
